word_embedding_cli.py
word_embedding_cli-0.0.1.data/data/wembcli_data/animals_300_50.model
word_embedding_cli-0.0.1.dist-info/entry_points.txt
word_embedding_cli-0.0.1.dist-info/LICENSE
word_embedding_cli-0.0.1.dist-info/WHEEL
word_embedding_cli-0.0.1.dist-info/METADATA
word_embedding_cli-0.0.1.dist-info/RECORD
