Metadata-Version: 2.1
Name: word_embedding_cli
Version: 0.0.1
Summary: Word Embedding CLI.
Author-email: Martim Bento <martimbento@gmail.com>, Gustavo Lourenço <pg47229@alunos.uminho.pt>
Classifier: License :: OSI Approved :: MIT License
Requires-Dist: typer
Requires-Dist: typing
Requires-Dist: gensim
Requires-Dist: colorama
